CHANGELOG.md
fastlife/__init__.py
fastlife/adapters/__init__.py
fastlife/adapters/fastapi/__init__.py
fastlife/adapters/fastapi/form.py
fastlife/adapters/fastapi/form_data.py
fastlife/adapters/fastapi/localizer.py
fastlife/adapters/fastapi/request.py
fastlife/adapters/fastapi/routing/__init__.py
fastlife/adapters/fastapi/routing/route.py
fastlife/adapters/fastapi/routing/router.py
fastlife/adapters/fastapi/websocket.py
fastlife/adapters/itsdangerous/__init__.py
fastlife/adapters/itsdangerous/session.py
fastlife/adapters/xcomponent/__init__.py
fastlife/adapters/xcomponent/functions/__init__.py
fastlife/adapters/xcomponent/functions/functions.py
fastlife/adapters/xcomponent/html/__init__.py
fastlife/adapters/xcomponent/html/collapsible.py
fastlife/adapters/xcomponent/html/form.py
fastlife/adapters/xcomponent/html/nav.py
fastlife/adapters/xcomponent/html/table.py
fastlife/adapters/xcomponent/html/text.py
fastlife/adapters/xcomponent/html/title.py
fastlife/adapters/xcomponent/icons/__init__.py
fastlife/adapters/xcomponent/icons/icons.py
fastlife/adapters/xcomponent/pydantic_form/__init__.py
fastlife/adapters/xcomponent/pydantic_form/components.py
fastlife/adapters/xcomponent/pydantic_form/widget_factory/__init__.py
fastlife/adapters/xcomponent/pydantic_form/widget_factory/base.py
fastlife/adapters/xcomponent/pydantic_form/widget_factory/bool_builder.py
fastlife/adapters/xcomponent/pydantic_form/widget_factory/date_builder.py
fastlife/adapters/xcomponent/pydantic_form/widget_factory/emailstr_builder.py
fastlife/adapters/xcomponent/pydantic_form/widget_factory/enum_builder.py
fastlife/adapters/xcomponent/pydantic_form/widget_factory/factory.py
fastlife/adapters/xcomponent/pydantic_form/widget_factory/ipaddr_builder.py
fastlife/adapters/xcomponent/pydantic_form/widget_factory/literal_builder.py
fastlife/adapters/xcomponent/pydantic_form/widget_factory/model_builder.py
fastlife/adapters/xcomponent/pydantic_form/widget_factory/secretstr_builder.py
fastlifeweb-0.40.0.dist-info/METADATA
fastlifeweb-0.40.0.dist-info/WHEEL
fastlifeweb-0.40.0.dist-info/entry_points.txt
fastlifeweb-0.40.0.dist-info/licenses/LICENSE
fastlifeweb-0.40.0.dist-info/RECORD
