Metadata-Version: 2.1
Name: fastlifeweb
Version: 0.40.0
Summary: High-level web framework
Author-Email: Guillaume Gauvrit <guillaume@gauvr.it>
License: MIT
Classifier: Development Status :: 4 - Beta
Classifier: Framework :: AsyncIO
Classifier: Intended Audience :: Developers
Classifier: License :: OSI Approved :: MIT License
Classifier: Topic :: Software Development :: Libraries :: Python Modules
Classifier: Topic :: Internet :: WWW/HTTP
Classifier: Typing :: Typed
Project-URL: Homepage, https://mardiros.github.io/fastlife
Project-URL: Documentation, https://mardiros.github.io/fastlife
Project-URL: Repository, https://github.com/mardiros/fastlife.git
Project-URL: Issues, https://github.com/mardiros/fastlife/issues
Project-URL: Changelog, https://mardiros.github.io/fastlife/user/changelog.html
Requires-Python: >=3.11
Requires-Dist: apscheduler<4,>=3.11.2
Requires-Dist: fastapi[standard]<0.123.0,>=0.122.0
Requires-Dist: itsdangerous<3,>=2.1.2
Requires-Dist: markupsafe<3,>=2.1.3
Requires-Dist: multidict<7,>=6.0.5
Requires-Dist: pydantic<3,>=2.7.0
Requires-Dist: pydantic-settings<3,>=2.0.3
Requires-Dist: python-multipart<1,>=0.0.13
Requires-Dist: venusian<4,>=3.0.0
Requires-Dist: xcomponent<1,>=0.11.0
Provides-Extra: testing
Requires-Dist: beautifulsoup4; extra == "testing"
Provides-Extra: docs
Requires-Dist: furo>=2024.5.6; extra == "docs"
Requires-Dist: heroicons<3,>=2.7.0; extra == "docs"
Requires-Dist: jinjax<0.49,>=0.48; extra == "docs"
Requires-Dist: linkify-it-py<3,>=2.0.3; extra == "docs"
Requires-Dist: myst-parser<5,>=4.0.0; extra == "docs"
Requires-Dist: sphinx<8,>=7.0.1; extra == "docs"
Requires-Dist: sphinx-autodoc2<1,>=0.5.0; extra == "docs"
